<?xml version="1.0" encoding="utf-8"?>
<resources xmlns:android="http://schemas.android.com/apk/res/android">
<string name="sign_in_to_chrome">"Banana Browser ಗೆ ಸೈನ್ ಇನ್ ಮಾಡಿ"</string>
<string name="sync_switch_title">"ನಿಮ್ಮ Banana Browser ಡೇಟಾವನ್ನು ಸಿಂಕ್ ಮಾಡಿ"</string>
<string name="usage_and_crash_reports_title">"Banana Browser ನ ವೈಶಿಷ್ಟ್ಯಗಳು ಹಾಗೂ ಕೆಲಸ ನಿರ್ವಹಣೆಯನ್ನು ಸುಧಾರಿಸಲು ಸಹಾಯ ಮಾಡಿ"</string>
<string name="autofill_describe_local_copy">"Banana Browser ಗೆ ನಕಲಿಸಲಾಗಿದೆ"</string>
<string name="save_password_preferences_export_action_description">"Banana Browser ಮೂಲಕ ಸಂಗ್ರಹಿಸಲಾದ ಪಾಸ್‌ವರ್ಡ್‌ಗಳನ್ನು ರಫ್ತು ಮಾಡಿ"</string>
<string name="save_password_preferences_export_subject">"Banana Browser ಪಾಸ್‌ವರ್ಡ್‌ಗಳು"</string>
<string name="safe_browsing_scout_reporting_title">"Banana Browser ಭದ್ರತೆಯನ್ನು ಸುಧಾರಿಸಲು ಸಹಾಯ ಮಾಡಿ"</string>
<string name="safe_browsing_scout_reporting_summary">"ಅಪಾಯಕಾರಿ ಆ್ಯಪ್‌ಗಳು ಮತ್ತು ಸೈಟ್‌ಗಳನ್ನು ಪತ್ತೆಹಚ್ಚಲು Banana Browser, ನೀವು ಭೇಟಿ ನೀಡುವ ಕೆಲವು ಪುಟಗಳ URL ಗಳು, ಸೀಮಿತ ಸಿಸ್ಟಂ ಮಾಹಿತಿ ಮತ್ತು ಕೆಲವು ಪುಟದ ವಿಷಯವನ್ನು Google ಗೆ ಕಳುಹಿಸುತ್ತದೆ"</string>
<string name="clear_browsing_data_history_dialog_title">"Banana Browser ಡೇಟಾ ತೆರವುಗೊಳಿಸಲಾಗಿದೆ"</string>
<string name="clear_browsing_data_history_dialog_data_text">"ಆಯ್ಕೆ ಮಾಡಿದ ಡೇಟಾವನ್ನು Banana Browser ನಿಂದ ಮತ್ತು ಸಿಂಕ್ ಮಾಡಿರುವ ನಿಮ್ಮ ಸಾಧನಗಳಿಂದ ತೆಗೆದುಹಾಕಲಾಗಿದೆ.
ನಿಮ್ಮ Google ಖಾತೆಯು, ಹುಡುಕಾಟಗಳು ಮತ್ತು ಇತರ Google ಸೇವೆಗಳ ಚಟುವಟಿಕೆಗಳಂತಹ ಬೇರೆ ವಿಧಗಳ ಬ್ರೌಸಿಂಗ್ ಇತಿಹಾಸವನ್ನು &lt;link&gt;myactivity.google.com&lt;/link&gt;.ನಲ್ಲಿ ಹೊಂದಿರಬಹುದು."</string>
<string name="android_permission_off_plural">"&lt;link&gt;Android ಸೆಟ್ಟಿಂಗ್‌ಗಳಲ್ಲಿ&lt;/link&gt; Banana Browser ಗೆ ಅನುಮತಿಗಳನ್ನು ಆನ್ ಮಾಡಿ."</string>
<string name="android_permission_off">"&lt;link&gt;Android ಸೆಟ್ಟಿಂಗ್‌ಗಳಲ್ಲಿ&lt;/link&gt; Banana Browser ಗೆ ಅನುಮತಿಯನ್ನು ಆನ್ ಮಾಡಿ."</string>
<string name="android_location_permission_off">"Banana Browser ನಿಮ್ಮ ಸ್ಥಳವನ್ನು ಪ್ರವೇಶಿಸುವುದಕ್ಕೆ ಅನುಮತಿಸಲು, &lt;link&gt;Android ಸೆಟ್ಟಿಂಗ್‌ಗಳಲ್ಲಿ&lt;/link&gt; ಸ್ಥಳವನ್ನು ಕೂಡ ಆನ್ ಮಾಡಬೇಕಾಗುತ್ತದೆ."</string>
<string name="android_camera_permission_off">"Banana Browser ನಿಮ್ಮ ಕ್ಯಾಮರಾವನ್ನು ಪ್ರವೇಶಿಸುವುದಕ್ಕೆ ಅನುಮತಿಸಲು, &lt;link&gt;Android ಸೆಟ್ಟಿಂಗ್‌ಗಳಲ್ಲಿ&lt;/link&gt; ಕ್ಯಾಮರಾವನ್ನು ಕೂಡ ಆನ್ ಮಾಡಬೇಕಾಗುತ್ತದೆ."</string>
<string name="android_notifications_permission_off">"Banana Browser ನಿಮಗೆ ಅಧಿಸೂಚನೆಗಳನ್ನು ಕಳುಹಿಸುವುದಕ್ಕೆ ಅನುಮತಿಸಲು, &lt;link&gt;Android ಸೆಟ್ಟಿಂಗ್‌ಗಳಲ್ಲಿ&lt;/link&gt; ಅಧಿಸೂಚನೆಗಳನ್ನು ಕೂಡ ಆನ್ ಮಾಡಬೇಕಾಗುತ್ತದೆ."</string>
<string name="android_microphone_permission_off">"Banana Browser ನಿಮ್ಮ ಮೈಕ್ರೋಫೋನ್‌ಗೆ ಪ್ರವೇಶಿಸುವುದಕ್ಕೆ ಅನುಮತಿಸಲು, &lt;link&gt;Android ಸೆಟ್ಟಿಂಗ್‌ಗಳಲ್ಲಿ&lt;/link&gt; ಮೈಕ್ರೋಫೋನ್ ಅನ್ನು ಕೂಡ ಆನ್ ಮಾಡಬೇಕಾಗುತ್ತದೆ."</string>
<string name="data_reduction_benefits_description_lite_mode">"ಲೈಟ್ ಮೋಡ್‍ನಲ್ಲಿ, Banana Browser ವೇಗವಾಗಿ ಪುಟಗಳನ್ನು ಲೋಡ್ ಮಾಡುತ್ತದೆ, ಮತ್ತು ಡೇಟಾವನ್ನು ಸುಮಾರು ಶೇಕಡಾ 60 ರಷ್ಟು ಕಡಿಮೆ ಬಳಸುತ್ತದೆ."</string>
<string name="data_reduction_description_lite_mode">"ಲೈಟ್ ಮೋಡ್ ಆನ್ ಆಗಿರುವಾಗ, ಪುಟಗಳು ವೇಗವಾಗಿ ಲೋಡ್ ಆಗುವಂತೆ ಮಾಡಲು, Google ಸರ್ವರ್‌ಗಳನ್ನು Banana Browser ಬಳಸುವುದು. ಅತ್ಯಗತ್ಯವಾದ ವಿಷಯವನ್ನು ಮಾತ್ರ ಲೋಡ್ ಮಾಡಲು, ಬಹಳ ನಿಧಾನವಾಗಿ ಲೋಡ್ ಆಗುವ ಪುಟಗಳನ್ನು ಲೈಟ್ ಮೋಡ್ ಪುನಃ ಬರೆಯುತ್ತದೆ. ಅದೃಶ್ಯ ಟ್ಯಾಬ್‌ಗಳಿಗೆ ಲೈಟ್ ಮೋಡ್ ಅನ್ವಯಿಸುವುದಿಲ್ಲ."</string>
<string name="data_reduction_usage_label">"Banana Browser ನಿಂದ ಬಳಕೆಯಾಗಿರುವ ಡೇಟಾ"</string>
<string name="data_reduction_promo_summary_lite_mode">"ಲೈಟ್ ಮೋಡ್‍ನಲ್ಲಿ, Banana Browser ವೇಗವಾಗಿ ಪುಟಗಳನ್ನು ಲೋಡ್ ಮಾಡುತ್ತದೆ, ಮತ್ತು ಸುಮಾರು ಶೇಕಡಾ 60 ರಷ್ಟು ಕಡಿಮೆ ಡೇಟಾವನ್ನು ಬಳಸುತ್ತದೆ. ನೀವು ಭೇಟಿ ನೀಡುವ ಪುಟಗಳನ್ನು ಆಪ್ಟಿಮೈಸ್ ಮಾಡಲು, Banana Browser ನಿಮ್ಮ ವೆಬ್ ಟ್ರಾಫಿಕ್ ಕುರಿತ ಮಾಹಿತಿಯನ್ನು Google ಗೆ ಕಳುಹಿಸುತ್ತದೆ. &lt;link&gt;ಇನ್ನಷ್ಟು ತಿಳಿಯಿರಿ&lt;/link&gt;"</string>
<string name="data_reduction_milestone_promo_text_mb">"ನಿಮ್ಮ %1$d MB ಅನ್ನು Banana Browser ಉಳಿಸಿದೆ"</string>
<string name="data_reduction_milestone_promo_text_gb">"ನಿಮ್ಮ %1$d GB ಅನ್ನು Banana Browser ಉಳಿಸಿದೆ"</string>
<string name="prefs_about_chrome">"Banana Browser ಕುರಿತು"</string>
<string name="deprecation_warning">"Android ನ ಈ ಆವೃತ್ತಿಯಲ್ಲಿ ಇನ್ನು ಮುಂದೆ Banana Browser ಅಪ್‌ಡೇಟ್‌ಗಳನ್ನು ಬೆಂಬಲಿಸಲಾಗುವುದಿಲ್ಲ"</string>
<string name="account_management_sign_out">"Banana Browser ನಿಂದ ಸೈನ್ ಔಟ್ ಮಾಡಿ"</string>
<string name="powered_by_chrome_message">"Banana Browser ನಿಂದ ಸಂಚಾಲಿತ"</string>
<string name="terms_of_service_title">"Banana Browser ಸೇವಾ ನಿಯಮಗಳು"</string>
<string name="privacy_notice_title">"Banana Browser ಗೌಪ್ಯತಾ ಸೂಚನೆ"</string>
<string name="signout_managed_account_title">"ಈ ಸಾಧನದಿಂದ ನಿಮ್ಮ Banana Browser ಡೇಟಾವನ್ನು ತೆರವುಗೊಳಿಸುವುದೇ?"</string>
<string name="signout_message">"ನಿಮ್ಮ ಬುಕ್‌ಮಾರ್ಕ್‌ಗಳು, ಇತಿಹಾಸ, ಪಾಸ್‌ವರ್ಡ್‌ಗಳು ಮತ್ತು ಇತರ Banana Browser ಡೇಟಾವನ್ನು ಇನ್ನು ಮುಂದೆ ನಿಮ್ಮ Google ಖಾತೆಗೆ ಸಿಂಕ್ ಮಾಡುವುದಿಲ್ಲ"</string>
<string name="remove_local_data">"ಈ ಸಾಧನದಿಂದ ನಿಮ್ಮ Banana Browser ಡೇಟಾವನ್ನು ಸಹ ತೆರವುಗೊಳಿಸಿ"</string>
<string name="signout_managed_account_message">"ನೀವು %1$s ಮೂಲಕ ನಿರ್ವಹಿಸಲಾಗುವ ಖಾತೆಯಿಂದ ಸೈನ್ ಔಟ್ ಮಾಡುತ್ತಿರುವ ಕಾರಣ, ಈ ಸಾಧನದಿಂದ ನಿಮ್ಮ Banana Browser ಡೇಟಾವನ್ನು ಅಳಿಸಲಾಗುತ್ತದೆ. ಇದು ನಿಮ್ಮ Google ಖಾತೆಯಲ್ಲಿ ಉಳಿಯುತ್ತದೆ."</string>
<string name="sign_in_managed_account_description">"%1$s ನಿರ್ವಹಿಸಿದ ಖಾತೆಯ ಮೂಲಕ ನೀವು ಸೈನ್‍‍ ಇನ್ ಮಾಡುತ್ತಿರುವಿರಿ ಮತ್ತು ಅದರ ನಿರ್ವಾಹಕ ನಿಯಂತ್ರಣವನ್ನು ನಿಮ್ಮ Banana Browser ಡೇಟಾದ ಮೂಲಕ ನೀಡುತ್ತಿರುವಿರಿ. ನಿಮ್ಮ ಡೇಟಾವನ್ನು ಶಾಶ್ವತವಾಗಿ ಈ ಖಾತೆಯೊಂದಿಗೆ ಜೋಡಿಸಲಾಗುತ್ತದೆ. Banana Browser ನಿಂದ ಸೈನ್ ಔಟ್ ಮಾಡುವುದರಿಂದ ಈ ಸಾಧನದಿಂದ ನಿಮ್ಮ ಡೇಟಾವನ್ನು ಅಳಿಸುತ್ತದೆ, ಆದರೆ ನಿಮ್ಮ Google ಖಾತೆಯಲ್ಲಿ ಸಂಗ್ರಹವಾಗಿಯೇ ಇರುತ್ತದೆ."</string>
<string name="ntp_recent_tabs_sync_promo_instructions">"ನಿಮ್ಮ ಇತರ ಸಾಧನಗಳಲ್ಲಿನ Banana Browser ನಲ್ಲಿ ನೀವು ತೆರೆದಿರುವಂತಹ ಟ್ಯಾಬ್‌ಗಳು ಇಲ್ಲಿ ಗೋಚರಿಸುತ್ತವೆ."</string>
<string name="bluetooth_unable_to_turn_on_adapter">"ಬ್ಲೂಟೂತ್ ಅಡಾಪ್ಟರ್ ಆನ್ ಮಾಡಲು Banana Browser ಗೆ ಸಾಧ್ಯವಾಗಲಿಲ್ಲ"</string>
<string name="bluetooth_need_location_permission">"ಸಾಧನಗಳನ್ನು ಸ್ಕ್ಯಾನ್ ಮಾಡಲು Banana Browser ಗೆ ಸ್ಥಳ ಪ್ರವೇಶ ಅಗತ್ಯವಿದೆ. &lt;permission_link&gt;ಅನುಮತಿಗಳನ್ನು ಅಪ್‌ಡೇಟ್ ಮಾಡಿ&lt;/permission_link&gt;"</string>
<string name="bluetooth_need_location_services_on">"ಸಾಧನಗಳನ್ನು ಸ್ಕ್ಯಾನ್ ಮಾಡಲು Banana Browser ಗೆ ಸ್ಥಳ ಪ್ರವೇಶ ಅಗತ್ಯವಿದೆ. ಸ್ಥಳ ಪ್ರವೇಶವನ್ನು &lt;services_link&gt;
ಈ ಸಾಧನಕ್ಕೆ ಆಫ್ ಮಾಡಲಾಗಿದೆ&lt;/services_link&gt;."</string>
<string name="bluetooth_need_location_permission_and_services_on">"ಸಾಧನಗಳನ್ನು ಸ್ಕ್ಯಾನ್ ಮಾಡಲು, Banana Browser ಗೆ ಸ್ಥಳ ಪ್ರವೇಶ ಅಗತ್ಯವಿದೆ. &lt;permission_link&gt;ಅನುಮತಿಗಳನ್ನು ಅಪ್‌ಡೇಟ್ ಮಾಡಿ&lt;/permission_link&gt;. ಸ್ಥಳ ಪ್ರವೇಶವನ್ನು ಸಹ &lt;services_link&gt;ಈ ಸಾಧನಕ್ಕೆ ಆಫ್ ಮಾಡಲಾಗಿದೆ&lt;/services_link&gt;."</string>
<string name="hint_android_sync_disabled">"Android ಸೆಟ್ಟಿಂಗ್‌ಗಳನ್ನು ತೆರೆಯಿರಿ ಮತ್ತು Banana Browser ಸಿಂಕ್ ಪ್ರಾರಂಭಿಸಲು Android ಸಿಸ್ಟಂ ಸಿಂಕ್ ಮರು-ಸಕ್ರಿಯಗೊಳಿಸಿ"</string>
<string name="hint_sync_settings_not_confirmed_description">"ಸಿಂಕ್ ಪ್ರಾರಂಭಿಸಲು, \"ನಿಮ್ಮ Banana Browser ಡೇಟಾ ಸಿಂಕ್ ಮಾಡಿ\" ಆಯ್ಕೆಯನ್ನು ಆನ್ ಮಾಡಿ."</string>
<string name="inline_update_infobar_ready_link_text">"Banana Browser ಮರುಪ್ರಾರಂಭಿಸಿ"</string>
<string name="inline_update_toast_downloading_message">"Banana Browser ಅಪ್‌ಡೇಟ್ ಡೌನ್‌ಲೋಡ್ ಮಾಡಲಾಗುತ್ತಿದೆ…"</string>
<string name="update_notification_title_default">"Banana Browser ಅಪ್‌ಡೇಟ್‌ ಮಾಡಿ"</string>
<string name="update_notification_text_body_default">"ಉತ್ತಮ ಬ್ರೌಸಿಂಗ್ ಅನುಭವಕ್ಕಾಗಿ, Banana Browser ಅನ್ನು ಅಪ್‌ಡೇಟ್‌ ಮಾಡಲು ತೆರೆಯಿರಿ"</string>
<string name="update_notification_title_experimental_update_chrome">"Banana Browser ಅಪ್‌ಡೇಟ್‌ ಮಾಡಿ"</string>
<string name="update_notification_text_body_experimental_update_chrome">"ನಿಮ್ಮ ಭಾಷೆಯಲ್ಲಿ ವೆಬ್ ಪುಟವನ್ನು ವೀಕ್ಷಿಸಲು, ಇತ್ತೀಚಿನ Banana Browser ಆವೃತ್ತಿಯನ್ನು ಪಡೆಯಿರಿ"</string>
<string name="update_notification_text_body_experimental_translate_the_web">"ನಿಮ್ಮ ಭಾಷೆಯನ್ನು Banana Browser ನ ಇತ್ತೀಚಿನ ಆವೃತ್ತಿಯಲ್ಲಿ ಪಡೆದುಕೊಳ್ಳಲು ಅಪ್‌ಡೇಟ್ ಮಾಡಿ"</string>
<string name="infobar_missing_camera_permission_text">"ಈ ಸೈಟ್‌ಗೆ ನಿಮ್ಮ ಕ್ಯಾಮರಾ ಪ್ರವೇಶಿಸಲು Banana Browser ಗೆ ಅನುಮತಿಸುವ ಅಗತ್ಯವಿದೆ."</string>
<string name="infobar_missing_microphone_permission_text">"ಈ ಸೈಟ್‌ಗೆ ನಿಮ್ಮ ಮೈಕ್ರೊಫೋನ್ ಪ್ರವೇಶಿಸಲು Banana Browser ಗೆ ಅನುಮತಿಸುವ ಅಗತ್ಯವಿದೆ."</string>
<string name="infobar_missing_microphone_camera_permissions_text">"ಈ ಸೈಟ್‌ಗೆ ನಿಮ್ಮ ಕ್ಯಾಮರಾ ಮತ್ತು ಮೈಕ್ರೊಫೋನ್ ಪ್ರವೇಶಿಸಲು Banana Browser ಗೆ ಅನುಮತಿಸುವ ಅಗತ್ಯವಿದೆ."</string>
<string name="infobar_missing_location_permission_text">"ಈ ಸೈಟ್‌ ಮೂಲಕ ನಿಮ್ಮ ಸ್ಥಳವನ್ನು ಹಂಚಿಕೊಳ್ಳಲು Banana Browser ಗೆ ನಿಮ್ಮ ಸ್ಥಳದ ಪ್ರವೇಶ ಅಗತ್ಯವಿದೆ."</string>
<string name="missing_storage_permission_download_education_text">"ಫೈಲ್‌ಗಳನ್ನು ಡೌನ್‌ಲೋಡ್ ಮಾಡಲು Banana Browser ಗೆ ಸಂಗ್ರಹಣೆ ಪ್ರವೇಶ ಅಗತ್ಯವಿದೆ."</string>
<string name="contextmenu_open_in_new_chrome_tab">"ಹೊಸ Banana Browser ಟ್ಯಾಬ್‌ನಲ್ಲಿ ತೆರೆಯಿರಿ"</string>
<string name="fre_activity_label">"Banana Browser ಮೊದಲ ರನ್ ಅನುಭವ"</string>
<string name="fre_tos_and_privacy">"ಈ ಅಪ್ಲಿಕೇಶನ್ ಬಳಸುವ ಮೂಲಕ, ನೀವು Banana Browser ನ &lt;LINK1&gt;ಸೇವಾ ನಿಯಮಗಳು&lt;/LINK1&gt; ಮತ್ತು &lt;LINK2&gt;ಗೌಪ್ಯತೆ ಪ್ರಕಟಣೆ&lt;/LINK2&gt;ಗೆ ಸಮ್ಮತಿಸುತ್ತೀರಿ."</string>
<string name="fre_tos_and_privacy_child_account">"ಈ ಅಪ್ಲಿಕೇಶನ್ ಬಳಸುವ ಮೂಲಕ, ನೀವು Banana Browser ನ &lt;LINK1&gt;ಸೇವಾ ನಿಯಮಗಳು&lt;/LINK1&gt; ಮತ್ತು &lt;LINK2&gt;ಗೌಪ್ಯತೆಯ ಸೂಚನೆ&lt;/LINK2&gt; ಗೆ ಮತ್ತು &lt;LINK3&gt;ಕುಟುಂಬದ ಲಿಂಕ್‌ನಲ್ಲಿ ನಿರ್ವಹಿಸಿದ Google ಖಾತೆಗಳಿಗಾಗಿ ಗೌಪ್ಯತಾ ಸೂಚನೆಗಳನ್ನು&lt;/LINK3&gt; ಸಮ್ಮತಿಸುತ್ತೀರಿ."</string>
<string name="lightweight_fre_associated_app_tos_and_privacy">"%1$s Banana Browser ನಲ್ಲಿ ತೆರೆಯುತ್ತದೆ. ಮುಂದುವರಿಸುವ ಮೂಲಕ, ನೀವು Banana Browser ನ &lt;LINK1&gt;ಸೇವಾ ನಿಯಮಗಳು&lt;/LINK1&gt; ಮತ್ತು &lt;LINK2&gt;ಗೌಪ್ಯತಾ ಸೂಚನೆ&lt;/LINK2&gt; ಗೆ ಒಪ್ಪುತ್ತಿರುವಿರಿ."</string>
<string name="lightweight_fre_associated_app_tos_and_privacy_child_account">"%1$s Banana Browser ನಲ್ಲಿ ತೆರೆಯುತ್ತದೆ. ಮುಂದುವರಿಸುವ ಮೂಲಕ, ನೀವು Banana Browser ನ &lt;LINK1&gt;ಸೇವಾ ನಿಯಮಗಳು&lt;/LINK1&gt; ಮತ್ತು &lt;LINK2&gt;ಗೌಪ್ಯತಾ ಸೂಚನೆ&lt;/LINK2&gt;, ಮತ್ತು &lt;LINK3&gt;ಕುಟುಂಬ ಲಿಂಕ್ ಮೂಲಕ Google ಖಾತೆಗಳಿಗಾಗಿ ನಿರ್ವಹಿಸಲಾದ ಗೌಪ್ಯತೆ ಸೂಚನೆ&lt;/LINK3&gt;ಗೆ ಸಮ್ಮತಿಸುತ್ತೀರಿ."</string>
<string name="fre_send_report_check">"Google ಗೆ ಬಳಕೆಯ ಅಂಕಿಅಂಶಗಳು ಮತ್ತು ಕ್ರ್ಯಾಶ್ ವರದಿಗಳನ್ನು ಕಳುಹಿಸುವ ಮೂಲಕ Banana Browser ಅನ್ನು ಉತ್ತಮಗೊಳಿಸಲು ಸಹಾಯ ಮಾಡಿ."</string>
<string name="fre_welcome">"Banana Browser ಗೆ ಸ್ವಾಗತ"</string>
<string name="menu_update">"Banana Browser ಅಪ್‌ಡೇಟ್‌ ಮಾಡಿ"</string>
<string name="menu_update_unsupported">"Banana Browser ಅಪ್‌ಡೇಟ್ ಮಾಡಲಾಗದು"</string>
<string name="menu_inline_update_ready_summary">"Banana Browser ಮರುಪ್ರಾರಂಭಿಸಿ"</string>
<string name="menu_open_in_chrome">"Banana Browser ನಲ್ಲಿ ತೆರೆಯಿರಿ"</string>
<string name="menu_open_in_incognito_chrome">"Open in Incognito Banana Browser"</string>
<string name="chrome_survey_prompt">"Banana Browser ಸುಧಾರಣೆಗೆ ಸಹಾಯ ಮಾಡಿ. &lt;LINK&gt;ಸಮೀಕ್ಷೆಯಲ್ಲಿ ಭಾಗವಹಿಸಿ&lt;/LINK&gt;"</string>
<string name="accessibility_toolbar_btn_menu_os_version_unsupported">"Banana Browser ಅಪ್‌ಡೇಟ್ ಮಾಡಲು ಸಾಧ್ಯವಿಲ್ಲ. ಇನ್ನಷ್ಟು ಆಯ್ಕೆಗಳು"</string>
<string name="unsupported_number_of_windows">"ಬೆಂಬಲಿಸದಿರುವ Banana Browser ನಿದರ್ಶನಗಳ ಸಂಖ್ಯೆ."</string>
<string name="storage_management_unimportant_site_data_description">"ಪ್ರಮುಖವಲ್ಲವೆಂದು Banana Browser ಭಾವಿಸುವ ಸೈಟ್ ಸಂಗ್ರಹಣೆ (ಉದಾ. ಯಾವುದೇ ಉಳಿಸದ ಸೆಟ್ಟಿಂಗ್‌ಗಳನ್ನು ಹೊಂದಿರುವ ಅಥವಾ ನೀವು ಆಗಾಗ್ಗೆ ಭೇಟಿ ನೀಡದ ಸೈಟ್‌ಗಳು)"</string>
<string name="storage_management_clear_unimportant_dialog_text">"ಇದು ಕುಕೀಗಳು, ಕ್ಯಾಷ್ ಮತ್ತು ಪ್ರಮುಖವಲ್ಲವೆಂದು Banana Browser ಭಾವಿಸುವ ಸೈಟ್‌ಗಳ ಇತರ ಡೇಟಾವನ್ನು ತೆರವುಗೊಳಿಸುತ್ತದೆ."</string>
<string name="storage_management_all_storage_description">"ಖಾತೆಗಳು, ಬುಕ್‌ಮಾರ್ಕ್‌ಗಳು ಮತ್ತು ಉಳಿಸಿದ ಸೆಟ್ಟಿಂಗ್‌ಗಳನ್ನು ಒಳಗೊಂಡಂತೆ Banana Browser ಬಳಸಿದ ಒಟ್ಟು ಡೇಟಾ"</string>
<string name="storage_management_reset_app_dialog_text">"ಎಲ್ಲಾ Banana Browser ಅಪ್ಲಿಕೇಶನ್ ಡೇಟಾವನ್ನು ಶಾಶ್ವತವಾಗಿ ಅಳಿಸಲಾಗುತ್ತದೆ. ಇದು ಎಲ್ಲಾ ಫೈಲ್‌ಗಳು, ಸೆಟ್ಟಿಂಗ್‌ಗಳು, ಖಾತೆಗಳು, ಡೇಟಾಬೇಸ್‌ಗಳು, ಇತ್ಯಾದಿಗಳನ್ನು ಒಳಗೊಂಡಿರುತ್ತದೆ."</string>
<string name="sogou_explanation">"Banana Browser ಚೀನಾದಲ್ಲಿ ಹುಡುಕಲು &lt;b&gt;Sogou&lt;/b&gt; ಬಳಸಬಹುದು. ನೀವು ಇದನ್ನು &lt;link&gt;ಸೆಟ್ಟಿಂಗ್‌ಗಳು&lt;/link&gt; ನಲ್ಲಿ ಬದಲಾಯಿಸಬಹುದು."</string>
<string name="app_running_in_chrome_disclosure">"ಈ ಆ್ಯಪ್‌, Banana Browser ನಲ್ಲಿ ರನ್ ಆಗುತ್ತಿದೆ"</string>
<string name="twa_running_in_chrome">"Banana Browser ನಲ್ಲಿ ಚಾಲನೆಯಾಗುತ್ತಿದೆ"</string>
<string name="twa_clear_data_dialog_title">"%1$sಆ್ಯಪ್‌ನ ಡೇಟಾವು Banana Browser ನಲ್ಲಿಯೂ ಇದೆ"</string>
<string name="twa_clear_data_dialog_message">"ನೀವು ಡೇಟಾವನ್ನು Banana Browser ಸೆಟ್ಟಿಂಗ್‌ಗಳಲ್ಲಿ ತೆರವುಗೊಳಿಸಬಹುದು"</string>
<string name="keyboard_shortcut_help_center">"ಹೊಸ ಟ್ಯಾಬ್‌ನಲ್ಲಿ Banana Browser ಸಹಾಯ ಕೇಂದ್ರ ತೆರೆಯಿರಿ"</string>
<string name="keyboard_shortcut_chrome_feature_group_header">"Google Banana Browser ವೈಶಿಷ್ಟ್ಯ ಶಾರ್ಟ್‌ಕಟ್‌ಗಳು"</string>
<string name="vr_preparing_vr_toast_standalone_text">"Banana Browser ಇನ್ನೂ VR ಗಾಗಿ ಸಿದ್ಧವಾಗುತ್ತಿದೆ. ಸ್ವಲ್ಪ ಸಮಯದ ನಂತರ Banana Browser ಅನ್ನು ಮರುಪ್ರಾರಂಭಿಸಿ."</string>
<string name="vr_preparing_vr_notification_body">"Banana Browser ಮರುತೆರೆಯಿರಿ."</string>
<string name="module_install_start_text">"Banana Browser ಗಾಗಿ %1$s ಇನ್‌ಸ್ಟಾಲ್ ಮಾಡಲಾಗುತ್ತಿದೆ…"</string>
<string name="module_install_failure_text">"Banana Browser ಗಾಗಿ %1$s ಇನ್‌ಸ್ಟಾಲ್ ಮಾಡಲು ಸಾಧ್ಯವಾಗಲಿಲ್ಲ"</string>
<string name="iph_download_infobar_downloads_are_faster_text">"Banana Browser ಈಗ ಫೈಲ್‌ಗಳನ್ನು ವೇಗವಾಗಿ ಡೌನ್‌ಲೋಡ್ ಮಾಡುತ್ತದೆ"</string>
<string name="sharing_no_devices_available_text">"ನಿಮ್ಮ ಫೋನ್‌ನಿಂದ ಮತ್ತೊಂದು ಸಾಧನಕ್ಕೆ ಏನನ್ನಾದರೂ ಹಂಚಿಕೊಳ್ಳಲು, ಎರಡೂ ಸಾಧನಗಳಲ್ಲಿರುವ, Banana Browser ಸೆಟ್ಟಿಂಗ್‌ಗಳಲ್ಲಿ ಸಿಂಕ್ ಅನ್ನು ಆನ್ ಮಾಡಿ"</string>
<string name="sharing_chrome_settings">"Go to Banana Browser ಸೆಟ್ಟಿಂಗ್‌ಗಳಿಗೆ ಹೋಗಿ"</string>
<string name="browser_sharing_error_dialog_text_device_not_found">"Banana Browser ನಲ್ಲಿ %1$s ಸಾಧನದ ಸಿಂಕ್ ಆನ್ ಆಗಿದೆಯೇ ಎಂದು ಖಚಿತಪಡಿಸಿಕೊಳ್ಳಿ"</string>
<string name="near_oom_intervention_message">"ಈ ಪುಟವು ಅತಿ ಹೆಚ್ಚು ಮೆಮೊರಿಯನ್ನು ಬಳಸಿಕೊಳ್ಳುತ್ತದೆ, ಆದ್ದರಿಂದ Banana Browser ಇದನ್ನು ವಿರಾಮಗೊಳಿಸಿದೆ."</string>
<string name="near_oom_reduction_message">"ಈ ಪುಟವು ತೀರಾ ಹೆಚ್ಚು ಮೆಮೊರಿಯನ್ನು ಬಳಸುತ್ತದೆ, ಆದ್ದರಿಂದ Banana Browser ಕೆಲವು ವಿಷಯಗಳನ್ನು ತೆಗೆದುಹಾಕಿದೆ."</string>
<string name="prefs_autofill_assistant_title">"Banana Browser ನಲ್ಲಿನ Google ಅಸಿಸ್ಟೆಂಟ್"</string>
<string name="usage_stats_consent_title">"ಡಿಜಿಟಲ್ ಯೋಗಕ್ಷೇಮದಲ್ಲಿ ನಿಮ್ಮ Banana Browser ಚಟುವಟಿಕೆಯನ್ನು ತೋರಿಸಲು ಬಯಸುವಿರಾ?"</string>
<string name="usage_stats_consent_prompt">"ನೀವು Banana Browser ನಲ್ಲಿ ಭೇಟಿ ಮಾಡಿದ ಸೈಟ್‌ಗಳನ್ನು ನೋಡಬಹುದು ಮತ್ತು ಅವುಗಳಿಗೆ ಟೈಮರ್‌ಗಳನ್ನು ಹೊಂದಿಸಬಹುದು.\n\nನೀವು ಯಾವ ಸೈಟ್‌ಗಳಿಗೆ  ಟೈಮರ್‌ಗಳನ್ನು ಹೊಂದಿಸಿದ್ದೀರಿ ಮತ್ತು  ಅವುಗಳಿಗೆ ಭೇಟಿ ಮಾಡಿ ಎಷ್ಟು ಸಮಯ ಕಳೆದಿರುವಿರಿ ಎನ್ನುವುದರ ಕುರಿತ ಮಾಹಿತಿಯನ್ನು Google ಪಡೆಯುತ್ತದೆ. ಡಿಜಿಟಲ್ ಯೋಗಕ್ಷೇಮವನ್ನು ಉತ್ತಮಗೊಳಿಸಲು ಈ ಮಾಹಿತಿಯನ್ನು ಬಳಸಲಾಗುವುದು."</string>
<string name="usage_stats_setting_title">"ಡಿಜಿಟಲ್ ಯೋಗಕ್ಷೇಮದಿಂದ ನಿಮ್ಮ Banana Browser ಚಟುವಟಿಕೆಯನ್ನು ತೆಗೆದುಹಾಕಿ"</string>
<string name="usage_stats_revocation_prompt">"ಡಿಜಿಟಲ್ ಯೋಗಕ್ಷೇಮದಿಂದ ನಿಮ್ಮ Banana Browser ಚಟುವಟಿಕೆಯನ್ನು ತೆಗೆದುಹಾಕಬೇಕೇ?"</string>
<string name="usage_stats_revocation_explanation">"Banana Browser ನಲ್ಲಿ ನೀವು ಭೇಟಿ ನೀಡುವ ಸೈಟ್‌ಗಳನ್ನು ತೋರಿಸುವುದಿಲ್ಲ. ಎಲ್ಲಾ ಸೈಟ್‌ ಟೈಮರ್‌ಗಳನ್ನು ಅಳಿಸಲಾಗುವುದು."</string>
<string name="autofill_assistant_module_title">"Banana Browser ನಲ್ಲಿನ Google ಅಸಿಸ್ಟೆಂಟ್"</string>
</resources>
